borsaiti/__init__.py
borsaiti/main.py
borsaiti-0.9.9.dist-info/licenses/LICENSE
borsaiti-0.9.9.dist-info/METADATA
borsaiti-0.9.9.dist-info/WHEEL
borsaiti-0.9.9.dist-info/top_level.txt
borsaiti-0.9.9.dist-info/RECORD
